.travis_testing.ini
MANIFEST.in
README.rst
development.ini.example
setup.py
testing.ini.example
openstax_accounts/__init__.py
openstax_accounts/authentication_policy.py
openstax_accounts/example.py
openstax_accounts/interfaces.py
openstax_accounts/openstax_accounts.py
openstax_accounts/stub.py
openstax_accounts/testing.ini
openstax_accounts/tests.py
openstax_accounts/utils.py
openstax_accounts/views.py
openstax_accounts.egg-info/PKG-INFO
openstax_accounts.egg-info/SOURCES.txt
openstax_accounts.egg-info/dependency_links.txt
openstax_accounts.egg-info/entry_points.txt
openstax_accounts.egg-info/not-zip-safe
openstax_accounts.egg-info/pbr.json
openstax_accounts.egg-info/requires.txt
openstax_accounts.egg-info/top_level.txt