Metadata-Version: 1.0
Name: openstax-accounts
Version: 1.0.0
Summary: An example pyramid app that connects to openstax/accounts
Home-page: http://github.com/Connexions/openstax-accounts
Author: Connexions team
Author-email: info@cnx.org
License: LGPL
Platform: UNKNOWN
